Metadata-Version: 2.1
Name: dynamodb-ce
Version: 0.0.5
Summary: A compiler for DynamoDB conditional expressions that returns an executable truthy function
Home-page: https://github.com/QuiNovas/dynamodb-conditional-expressions
Author: Joseph Wortmann
Author-email: jwortmann@quinovas.com
License: Apache 2.0
Platform: UNKNOWN
Classifier: Development Status :: 4 - Beta
Classifier: Intended Audience :: Developers
Classifier: License :: OSI Approved :: Apache Software License
Classifier: Programming Language :: Python :: 3.8
License-File: LICENSE
